uhura/__init__.py
uhura/base.py
uhura/caches.py
uhura/caching.py
uhura/comparison.py
uhura/composition.py
uhura/decorables.py
uhura/functional.py
uhura/modes.py
uhura/pandas_tools.py
uhura/serde.py
uhura/properties/__init__.py
uhura/properties/homomorphic_hash.py
uhura/properties/property_tester.py
uhura/properties/testable_properties.py
uhura/properties/transformer.py
uhura-2.2.3.dist-info/AUTHORS
uhura-2.2.3.dist-info/LICENSE
uhura-2.2.3.dist-info/METADATA
uhura-2.2.3.dist-info/WHEEL
uhura-2.2.3.dist-info/pbr.json
uhura-2.2.3.dist-info/top_level.txt
uhura-2.2.3.dist-info/RECORD
