Metadata-Version: 2.1
Name: uhura
Version: 2.2.3
Summary: Wrapper code for cleaning up IO
Home-page: UNKNOWN
Author: Declan Crew
Author-email: declan.crew@vortexa.com
License: MIT
Keywords: setup,distutils
Platform: UNKNOWN
Classifier: Development Status :: 4 - Beta
Classifier: Intended Audience :: Developers
Classifier: Intended Audience :: Information Technology
Classifier: Operating System :: OS Independent
Classifier: Programming Language :: Python
Requires-Python: >=3.7
Requires-Dist: pandas (>=2.0.0)
Requires-Dist: graphlib-backport
Provides-Extra: build
Requires-Dist: setuptools ; extra == 'build'
Requires-Dist: twine ; extra == 'build'
Requires-Dist: wheel ; extra == 'build'
Provides-Extra: dev
Requires-Dist: aioboto3 (~=9.6.0) ; extra == 'dev'
Requires-Dist: aiobotocore (~=2.3.0) ; extra == 'dev'
Requires-Dist: aiohttp (~=3.8.1) ; extra == 'dev'
Requires-Dist: aioitertools (~=0.10.0) ; extra == 'dev'
Requires-Dist: aiosignal (~=1.2.0) ; extra == 'dev'
Requires-Dist: async-timeout (~=4.0.2) ; extra == 'dev'
Requires-Dist: attrs (~=21.4.0) ; extra == 'dev'
Requires-Dist: black (~=22.3.0) ; extra == 'dev'
Requires-Dist: boto3 (~=1.21.21) ; extra == 'dev'
Requires-Dist: botocore (~=1.24.21) ; extra == 'dev'
Requires-Dist: cfgv (~=3.3.1) ; extra == 'dev'
Requires-Dist: charset-normalizer (~=2.1.0) ; extra == 'dev'
Requires-Dist: click (~=8.1.3) ; extra == 'dev'
Requires-Dist: coverage (~=6.4.1) ; extra == 'dev'
Requires-Dist: distlib (~=0.3.4) ; extra == 'dev'
Requires-Dist: filelock (~=3.7.1) ; extra == 'dev'
Requires-Dist: flake8 (~=4.0.1) ; extra == 'dev'
Requires-Dist: frozenlist (~=1.3.0) ; extra == 'dev'
Requires-Dist: identify (~=2.5.1) ; extra == 'dev'
Requires-Dist: idna (~=3.3) ; extra == 'dev'
Requires-Dist: iniconfig (~=1.1.1) ; extra == 'dev'
Requires-Dist: jmespath (~=1.0.1) ; extra == 'dev'
Requires-Dist: logzero (~=1.7.0) ; extra == 'dev'
Requires-Dist: mccabe (~=0.6.1) ; extra == 'dev'
Requires-Dist: multidict (~=6.0.2) ; extra == 'dev'
Requires-Dist: mypy-extensions (~=0.4.3) ; extra == 'dev'
Requires-Dist: nodeenv (~=1.6.0) ; extra == 'dev'
Requires-Dist: numexpr (~=2.8.1) ; extra == 'dev'
Requires-Dist: numpy (~=1.22.4) ; extra == 'dev'
Requires-Dist: packaging (~=21.3) ; extra == 'dev'
Requires-Dist: pandas (~=1.4.2) ; extra == 'dev'
Requires-Dist: pathspec (~=0.9.0) ; extra == 'dev'
Requires-Dist: platformdirs (~=2.5.2) ; extra == 'dev'
Requires-Dist: pluggy (~=1.0.0) ; extra == 'dev'
Requires-Dist: pre-commit (~=2.19.0) ; extra == 'dev'
Requires-Dist: py (~=1.11.0) ; extra == 'dev'
Requires-Dist: pyarrow (~=8.0.0) ; extra == 'dev'
Requires-Dist: pycodestyle (~=2.8.0) ; extra == 'dev'
Requires-Dist: pycryptodomex (~=3.14.1) ; extra == 'dev'
Requires-Dist: pyflakes (~=2.4.0) ; extra == 'dev'
Requires-Dist: pyparsing (~=3.0.9) ; extra == 'dev'
Requires-Dist: pytest (~=7.1.2) ; extra == 'dev'
Requires-Dist: pytest-cov (~=3.0.0) ; extra == 'dev'
Requires-Dist: python-dateutil (~=2.8.2) ; extra == 'dev'
Requires-Dist: pytz (~=2022.1) ; extra == 'dev'
Requires-Dist: PyYAML (~=6.0) ; extra == 'dev'
Requires-Dist: s3transfer (~=0.5.2) ; extra == 'dev'
Requires-Dist: six (~=1.16.0) ; extra == 'dev'
Requires-Dist: tables (~=3.7.0) ; extra == 'dev'
Requires-Dist: toml (~=0.10.2) ; extra == 'dev'
Requires-Dist: tomli (~=2.0.1) ; extra == 'dev'
Requires-Dist: typing-extensions (~=4.2.0) ; extra == 'dev'
Requires-Dist: urllib3 (~=1.26.9) ; extra == 'dev'
Requires-Dist: virtualenv (~=20.14.1) ; extra == 'dev'
Requires-Dist: wrapt (~=1.14.1) ; extra == 'dev'
Requires-Dist: yarl (~=1.7.2) ; extra == 'dev'
Provides-Extra: pandas
Requires-Dist: pandas ; extra == 'pandas'
Provides-Extra: test
Requires-Dist: black ; extra == 'test'
Requires-Dist: flake8 ; extra == 'test'
Requires-Dist: pytest ; extra == 'test'
Requires-Dist: pytest-cov ; extra == 'test'
Requires-Dist: pandas ; extra == 'test'
Requires-Dist: pyarrow ; extra == 'test'
